{
	"instance" : {
		"complete" : " 3/21/2018 15:22:28",
		"window" : " 3/21/2018 15:22:28",
		"compareWith:" : " 3/21/2018 15:22:28",
		"initialize" : " 3/21/2018 15:22:28",
		"popc" : " 3/21/2018 15:22:28",
		"process:" : " 3/21/2018 15:22:28",
		"compareHexDigestWith:" : " 3/21/2018 15:22:28",
		"accumulator:" : " 3/21/2018 15:22:28",
		"window:" : " 3/21/2018 15:22:28",
		"tran" : " 3/21/2018 15:22:28",
		"complete:" : " 3/21/2018 15:22:28",
		"incrementAccumulatorAt:" : " 3/21/2018 15:22:28",
		"incrementNumChar" : " 3/21/2018 15:22:28",
		"numChar" : " 3/21/2018 15:22:28",
		"data:" : " 3/21/2018 15:22:28",
		"accumulator" : " 3/21/2018 15:22:28",
		"tran53HashA:b:c:n:" : " 3/21/2018 15:22:28",
		"numChar:" : " 3/21/2018 15:22:28",
		"hexDigest" : " 3/21/2018 15:22:28",
		"digest" : " 3/21/2018 15:22:28",
		"computeDigest" : " 3/21/2018 15:22:28"
	},
	"class" : {
		"new:" : " 3/21/2018 15:22:28",
		"compareDigest:with:" : " 3/21/2018 15:22:28"
	}
}